{
  "title": "Iasmin Lisboa | Desenvolvedora Front-end | React, Shopify e SEO",
  "jobTitle": "Desenvolvedora Front-end",
  "description": "Desenvolvedora front-end especializada em React, TypeScript e e-commerce (Shopify e VTEX), com foco em SEO técnico, performance, acessibilidade e interfaces de alta qualidade.",
  "image": "/images/image-preview-url.png",
  "altImagem": "Foto de perfil da Iasmin Lisboa, desenvolvedora front-end",
  "author": "Iasmin Lisboa Nogueira",
  "keywords": "desenvolvedora front-end, React, TypeScript, E-commerce, Shopify, SEO técnico, desenvolvimento web",
  "favicon": "/images/favicon.png"
}
